moveread/datasets/__init__.py
moveread/datasets/main.py
moveread_datasets-0.1.6.dist-info/METADATA
moveread_datasets-0.1.6.dist-info/WHEEL
moveread_datasets-0.1.6.dist-info/top_level.txt
moveread_datasets-0.1.6.dist-info/RECORD
